ase_template/__init__.py
ase_template-0.1.1.dist-info/WHEEL
ase_template-0.1.1.dist-info/entry_points.txt
ase_template-0.1.1.dist-info/METADATA
ase_template-0.1.1.dist-info/RECORD
