Metadata-Version: 2.3
Name: ase-template
Version: 0.1.1
Summary: Agentic software engineering (ASE) template
Author: Cody
Author-email: Cody <cody@dkdc.dev>
Requires-Python: >=3.13
